acapi/__init__.py
acapi/client.py
acapi/exceptions.py
acapi/version.py
acapi/resources/__init__.py
acapi/resources/acquiadata.py
acapi/resources/acquialist.py
acapi/resources/acquiaresource.py
acapi/resources/backup.py
acapi/resources/backuplist.py
acapi/resources/database.py
acapi/resources/databaselist.py
acapi/resources/domain.py
acapi/resources/domainlist.py
acapi/resources/environment.py
acapi/resources/environmentlist.py
acapi/resources/server.py
acapi/resources/serverlist.py
acapi/resources/site.py
acapi/resources/sitelist.py
acapi/resources/task.py
acapi/resources/tasklist.py
acapi/resources/user.py
acapi-0.8.1.dist-info/LICENSE
acapi-0.8.1.dist-info/METADATA
acapi-0.8.1.dist-info/WHEEL
acapi-0.8.1.dist-info/top_level.txt
acapi-0.8.1.dist-info/RECORD
