Metadata-Version: 2.1
Name: acapi
Version: 0.8.1
Summary: Acquia Cloud API client.
Home-page: http://github.com/skwashd/python-acquia-cloud
Author: Dave Hall
Author-email: me@davehall.com.au
License: MIT
Platform: UNKNOWN
Classifier: Development Status :: 4 - Beta
Classifier: Topic :: Internet
Classifier: Intended Audience :: Developers
Classifier: License :: OSI Approved :: MIT License
Classifier: Operating System :: OS Independent
Classifier: Programming Language :: Python
Classifier: Programming Language :: Python :: 3
Classifier: Programming Language :: Python :: 3.6
Classifier: Programming Language :: Python :: 3.7
Requires-Dist: requests (==2.22.0)
Requires-Dist: requests-cache (==0.5.2)
